amaasutils/__init__.py
amaasutils/case.py
amaasutils/holiday_mapping.py
amaasutils/logging_utils.py
amaasutils/param_utils.py
amaasutils/random_utils.py
amaasutils-1.2.0.dist-info/DESCRIPTION.rst
amaasutils-1.2.0.dist-info/METADATA
amaasutils-1.2.0.dist-info/RECORD
amaasutils-1.2.0.dist-info/WHEEL
amaasutils-1.2.0.dist-info/metadata.json
amaasutils-1.2.0.dist-info/top_level.txt
